deabook/CNLSSDFDDF.py
deabook/CNLSSDFDDFweak.py
deabook/CNLSSDFDDFweakmeta.py
deabook/DDFDUAL.py
deabook/DEA.py
deabook/DEAweak.py
deabook/DRFDUAL.py
deabook/MB.py
deabook/MQDEA.py
deabook/MQDEAweak.py
deabook/StoNED.py
deabook/__init__.py
deabook/common.py
deabook/constant.py
deabook/deabook.py
deabook/data/41Firm.csv
deabook/data/Ex3.dta
deabook/data/Ex4.dta
deabook/data/Ex5.dta
deabook/data/aaa.xls
deabook/data/abatementCost.csv
deabook/data/china data.xlsx
deabook/data/electricityFirms.csv
deabook/data/oecd data.xlsx
deabook/data/power plant data.xlsx
deabook/data/riceProduction.csv
deabook/example/chap12/chap12.ipynb
deabook/example/chap13/chap13.ipynb
deabook/example/chap14/chap14.ipynb
deabook/example/chap15/chap15.ipynb
deabook/example/chap2/DDF_CRS.md
deabook/example/chap2/DDF_VRS.md
deabook/example/chap2/DDF_VRS_province.md
deabook/example/chap2/DEA_CRS.md
deabook/example/chap2/DEA_VRS.md
deabook/example/chap2/HYPER_CRS.md
deabook/example/chap2/HYPER_VRS.md
deabook/example/chap2/chap 2_country.ipynb
deabook/example/chap2/chap 2_province.ipynb
deabook/example/chap2/chap2分国家资本效率.png
deabook/example/chap2/chap2分年份地区资本效率-省.png
deabook/example/chap2/chap2分年份资本效率-国.png
deabook/example/chap2/chap2分年份资本效率-省.png
deabook/example/chap2/chap2分省份资本效率.png
deabook/example/chap3/MQDDF_CRS.md
deabook/example/chap3/MQDDF_VRS.md
deabook/example/chap3/MQDEA_CRS - 副本.xlsx
deabook/example/chap3/MQDEA_CRS.md
deabook/example/chap3/MQDEA_CRS.xlsx
deabook/example/chap3/MQDEA_VRS_.md
deabook/example/chap3/chap 3.ipynb
deabook/example/chap3/chap 3_province.ipynb
deabook/example/chap3/chap3分国家产出效率.png
deabook/example/chap3/chap3分年份产出效率-国.png
deabook/example/chap3/chap3分年份产出效率-省.png
deabook/example/chap3/chap3分省份产出效率.png
deabook/example/chap3/table3.1.md
deabook/example/chap3/table3.2_MQDEA_VRS_.md
deabook/example/chap3/table3.3_MQDDF_VRS.md
deabook/example/chap3/table3.4.md
deabook/example/chap4/DDF_VRS.md
deabook/example/chap4/MQDEA_VRS_.md
deabook-0.0.9.dist-info/licenses/LICENSE
deabook-0.0.9.dist-info/METADATA
deabook-0.0.9.dist-info/WHEEL
deabook-0.0.9.dist-info/entry_points.txt
deabook-0.0.9.dist-info/top_level.txt
deabook-0.0.9.dist-info/RECORD
