Metadata-Version: 2.4
Name: deabook
Version: 0.0.9
Summary: dea
Author-email: advancehs <1019753743@qq.com>
License: MIT License
Project-URL: Homepage, https://github.com/advancehs/deabook
Keywords: deabook
Classifier: Intended Audience :: Developers
Classifier: License :: OSI Approved :: MIT License
Classifier: Natural Language :: English
Classifier: Programming Language :: Python :: 3.8
Classifier: Programming Language :: Python :: 3.9
Classifier: Programming Language :: Python :: 3.10
Classifier: Programming Language :: Python :: 3.11
Classifier: Programming Language :: Python :: 3.12
Requires-Python: >=3.8
License-File: LICENSE
Requires-Dist: pyomo>=6.9.2
Requires-Dist: mosek>=11.0.19
Requires-Dist: pandas>=2.2.3
Requires-Dist: openpyxl
Requires-Dist: numpy>=2.0.0
Requires-Dist: scipy>=1.13.0
Requires-Dist: matplotlib>=3.9.0
Requires-Dist: ipykernel
Requires-Dist: tabulate
Requires-Dist: pyscipopt
Provides-Extra: all
Requires-Dist: deabook[extra]; extra == "all"
Provides-Extra: extra
Requires-Dist: pandas; extra == "extra"
Dynamic: license-file
